{
  "$type": "ThunderRoad.LootTable, ThunderRoad",
  "id": "MCW.LootTable.RareLongFace",
  "sensitiveContent": "None",
  "sensitiveFilterBehaviour": "Discard",
  "version": 1,
  "levelledDrops": [
    {
      "$type": "ThunderRoad.LootTable+DropLevel, ThunderRoad",
      "dropLevel": 0,
      "drops": [
        {
          "$type": "ThunderRoad.LootTable+Drop, ThunderRoad",
          "referenceID": "MCW.BalaclavaHBLK",
          "reference": "Item",
          "randMode": "ItemCount",
          "minMaxRand": {
            "x": 1.0,
            "y": 1.0
          },
          "probabilityWeight": 1.0
        },
        {
          "$type": "ThunderRoad.LootTable+Drop, ThunderRoad",
          "referenceID": "MCW.PTGOffBLKO",
          "reference": "Item",
          "randMode": "ItemCount",
          "minMaxRand": {
            "x": 1.0,
            "y": 1.0
          },
          "probabilityWeight": 0.5
        },
        {
          "$type": "ThunderRoad.LootTable+Drop, ThunderRoad",
          "referenceID": "MCW.PTGOnBLKO",
          "reference": "Item",
          "randMode": "ItemCount",
          "minMaxRand": {
            "x": 1.0,
            "y": 1.0
          },
          "probabilityWeight": 0.5
        }
      ]
    }
  ],
  "groupPath": "Armors"
}